pyradiate/__init__.py
pyradiate-0.1.dist-info/LICENSE
pyradiate-0.1.dist-info/METADATA
pyradiate-0.1.dist-info/WHEEL
pyradiate-0.1.dist-info/top_level.txt
pyradiate-0.1.dist-info/RECORD
